aient/__init__.py
aient/architext/architext/__init__.py
aient/architext/architext/core.py
aient/architext/test/openai_client.py
aient/architext/test/test.py
aient/architext/test/test_save_load.py
aient/core/__init__.py
aient/core/log_config.py
aient/core/models.py
aient/core/request.py
aient/core/response.py
aient/core/utils.py
aient/core/test/test_base_api.py
aient/core/test/test_geminimask.py
aient/core/test/test_image.py
aient/core/test/test_payload.py
aient/models/__init__.py
aient/models/audio.py
aient/models/base.py
aient/models/chatgpt.py
aient/plugins/__init__.py
aient/plugins/arXiv.py
aient/plugins/config.py
aient/plugins/excute_command.py
aient/plugins/get_time.py
aient/plugins/image.py
aient/plugins/list_directory.py
aient/plugins/read_image.py
aient/plugins/readonly.py
aient/plugins/registry.py
aient/plugins/run_python.py
aient/plugins/websearch.py
aient/utils/__init__.py
aient/utils/prompt.py
aient/utils/scripts.py
aient-1.2.57.dist-info/licenses/LICENSE
aient-1.2.57.dist-info/METADATA
aient-1.2.57.dist-info/WHEEL
aient-1.2.57.dist-info/top_level.txt
aient-1.2.57.dist-info/RECORD
