Metadata-Version: 2.4
Name: aient
Version: 1.2.57
Summary: Aient: The Awakening of Agent.
Requires-Python: >=3.11
License-File: LICENSE
Requires-Dist: beautifulsoup4>=4.13.4
Requires-Dist: chardet>=5.2.0
Requires-Dist: duckduckgo-search==5.3.1
Requires-Dist: fake-useragent>=2.2.0
Requires-Dist: fastapi>=0.116.1
Requires-Dist: html2text>=2025.4.15
Requires-Dist: httpx>=0.28.1
Requires-Dist: httpx-socks>=0.10.1
Requires-Dist: lxml-html-clean>=0.4.2
Requires-Dist: msgspec>=0.19.0
Requires-Dist: pdfminer-six==20240706
Requires-Dist: pillow>=11.3.0
Requires-Dist: pytz>=2025.2
Requires-Dist: requests>=2.32.4
Dynamic: license-file
